paperpc/__init__.py
paperpc/__main__.py
paperpc/cmd.py
paperpc/config.py
paperpc/main.py
paperpc/parts.py
paperpc-0.4.2.dist-info/licenses/LICENSE
paperpc-0.4.2.dist-info/METADATA
paperpc-0.4.2.dist-info/WHEEL
paperpc-0.4.2.dist-info/entry_points.txt
paperpc-0.4.2.dist-info/top_level.txt
paperpc-0.4.2.dist-info/RECORD
