Metadata-Version: 2.4
Name: PaperPC
Version: 0.4.2
Summary: Python implementation of the Little Man Computer with additional SFT instruction.
Author-email: Douglas Luman <dluman@allegheny.edu>
License-File: LICENSE
Requires-Dist: arglite
Requires-Dist: pyyaml
Dynamic: license-file
